s3psync/__init__.py
s3psync/__main__.py
s3psync/core.py
s3psync/s3cli.py
s3psync-0.0.6.dist-info/AUTHORS.md
s3psync-0.0.6.dist-info/LICENSE
s3psync-0.0.6.dist-info/METADATA
s3psync-0.0.6.dist-info/WHEEL
s3psync-0.0.6.dist-info/entry_points.txt
s3psync-0.0.6.dist-info/top_level.txt
s3psync-0.0.6.dist-info/RECORD
