Metadata-Version: 2.1
Name: s3psync
Version: 0.0.6
Summary: s3psync: A simple tool to sync files and directories to Amazon S3.
Author: Prem Rara
Author-email: p@rara.dev
License: MIT
Requires-Python: >=3.9
License-File: LICENSE
License-File: AUTHORS.md
Requires-Dist: pip
Requires-Dist: boto3
Requires-Dist: click
Requires-Dist: colorama >=0.2.4 ; sys_platform == "win32"
Provides-Extra: dev
Requires-Dist: pytest ; extra == 'dev'
Requires-Dist: flake8 ; extra == 'dev'
Requires-Dist: bump-my-version ; extra == 'dev'
Provides-Extra: test
Requires-Dist: pytest ; extra == 'test'
